README.rst
consul.py
setup.py
consul_service_discovery.egg-info/PKG-INFO
consul_service_discovery.egg-info/SOURCES.txt
consul_service_discovery.egg-info/dependency_links.txt
consul_service_discovery.egg-info/requires.txt
consul_service_discovery.egg-info/top_level.txt