Metadata-Version: 1.1
Name: consul-service-discovery
Version: 0.1.2
Summary: Python client for Consul Service Discovery API
Home-page: https://github.com/javicacheiro/consul-service-discovery
Author: Javier Cacheiro
Author-email: javier.cacheiro@gmail.com
License: MIT
Platform: UNKNOWN
Classifier: License :: OSI Approved :: MIT License
Classifier: Intended Audience :: Developers
Classifier: Intended Audience :: System Administrators
Classifier: Operating System :: OS Independent
Classifier: Topic :: Software Development :: Libraries :: Python Modules
